hello_world/__init__.py
hello_world/client.py
hello_world_cc2-0.0.9.dist-info/LICENSE
hello_world_cc2-0.0.9.dist-info/METADATA
hello_world_cc2-0.0.9.dist-info/WHEEL
hello_world_cc2-0.0.9.dist-info/top_level.txt
hello_world_cc2-0.0.9.dist-info/RECORD
